ripy/__init__.py
ripy/libri.dll
ripy/ripy.cp311-win_amd64.pyd
ri_python-1.0.0.dist-info/LICENSE.txt
ri_python-1.0.0.dist-info/METADATA
ri_python-1.0.0.dist-info/WHEEL
ri_python-1.0.0.dist-info/top_level.txt
ri_python-1.0.0.dist-info/RECORD
