Metadata-Version: 2.1
Name: ri-python
Version: 1.0.0
Summary: Resolved Instruments Python library
Home-page: https://resolvedinstruments.com
Author: Callum Doolin
Author-email: callum@resolvedinstruments.com
License: Reference only
Project-URL: Documentation, https://resolvedinstruments.com/docs/ripy-toc.html
Classifier: License :: Other/Proprietary License
Classifier: Programming Language :: Python :: 3.5
Classifier: Programming Language :: Python :: 3.6
Classifier: Programming Language :: Python :: 3.7
Classifier: Programming Language :: Python :: 3.8
Classifier: Programming Language :: Python :: 3.9
Classifier: Programming Language :: Python :: 3.10
Classifier: Programming Language :: Python :: 3.11
Classifier: Programming Language :: Python :: 3.12
Requires-Python: >=2.7
License-File: LICENSE.txt
Requires-Dist: numpy
